kaga_logger/__init__.py
kaga_logger/logger.py
kaga_logger_kagamino-0.1.3.dist-info/LICENSE
kaga_logger_kagamino-0.1.3.dist-info/METADATA
kaga_logger_kagamino-0.1.3.dist-info/WHEEL
kaga_logger_kagamino-0.1.3.dist-info/top_level.txt
kaga_logger_kagamino-0.1.3.dist-info/RECORD
