Metadata-Version: 2.1
Name: kaga-logger-kagamino
Version: 0.1.3
Summary: A simple colored logger for python projects
Home-page: https://github.com/martinlehoux/kaga-logger
Author: Martin Kagamino Lehoux
Author-email: martin@lehoux.net
License: UNKNOWN
Platform: UNKNOWN
Classifier: Programming Language :: Python :: 3
Classifier: License :: OSI Approved :: MIT License
Requires-Python: >=3.7
